setup.py
mhexport/MH_export_extract.py
mhexport/__init__.py
mhexport.egg-info/PKG-INFO
mhexport.egg-info/SOURCES.txt
mhexport.egg-info/dependency_links.txt
mhexport.egg-info/not-zip-safe
mhexport.egg-info/top_level.txt