Metadata-Version: 2.1
Name: mhexport
Version: 0.2
Summary: Mass Hunter Raw Data Export to Dataframe
Home-page: UNKNOWN
License: UNKNOWN
Platform: UNKNOWN
